label_studio_tools/__init__.py
label_studio_tools/core/__init__.py
label_studio_tools/core/label_config.py
label_studio_tools/core/utils/__init__.py
label_studio_tools/core/utils/exceptions.py
label_studio_tools/core/utils/io.py
label_studio_tools/core/utils/params.py
label_studio_tools/postprocessing/__init__.py
label_studio_tools/postprocessing/video.py
label_studio_tools/tests/__init__.py
label_studio_tools/tests/test_core_label_config.py
label_studio_tools/tests/test_postprocessing_video.py
koistudio_tools-0.0.3.post1.dist-info/LICENSE
koistudio_tools-0.0.3.post1.dist-info/METADATA
koistudio_tools-0.0.3.post1.dist-info/WHEEL
koistudio_tools-0.0.3.post1.dist-info/top_level.txt
koistudio_tools-0.0.3.post1.dist-info/RECORD
